<config xmlns="http://tail-f.com/ns/config/1.0">
  <environments xmlns="https://curity.se/ns/conf/base">
    <environment>
      <base-url>#{RUNTIME_BASE_URL}</base-url>
      <admin-service>
        <http>
          <base-url>#{ADMIN_BASE_URL}</base-url>
          <web-ui>
          </web-ui>
          <restconf>
          </restconf>
        </http>
      </admin-service>
      <services>
        <zones>
          <default-zone>
            <symmetric-key>#{SYMMETRIC_KEY}</symmetric-key>
          </default-zone>
        </zones>
        <service-role>
          <id>default</id>
          <protocol>http</protocol>
          <webfinger/>
          <endpoints>applications</endpoints>
          <endpoints>authentication-service-anonymous</endpoints>
          <endpoints>authentication-service-authentication</endpoints>
          <endpoints>authentication-service-registration</endpoints>
          <endpoints>token-service-anonymous</endpoints>
          <endpoints>token-service-assisted-token</endpoints>
          <endpoints>token-service-authorize</endpoints>
          <endpoints>token-service-introspect</endpoints>
          <endpoints>token-service-revoke</endpoints>
          <endpoints>token-service-session</endpoints>
          <endpoints>token-service-token</endpoints>
          <endpoints>token-service-userinfo</endpoints>
        </service-role>
      </services>
    </environment>
  </environments>
  <facilities xmlns="https://curity.se/ns/conf/base">
    <data-sources>
      <data-source>
        <id>default-datasource</id>
        <jdbc xmlns="https://curity.se/ns/ext-conf/jdbc">
          <connection-string>#{DB_CONNECTION}</connection-string>
          <standard-credentials-mode>
          </standard-credentials-mode>
          <driver>org.hsqldb.jdbc.JDBCDriver</driver>
          <password>#{DB_PASSWORD}</password>
          <username>#{DB_USER}</username>
        </jdbc>
      </data-source>
    </data-sources>
    <crypto>
      <signing-keys>
        <signing-key>
          <id>default-signing-key</id>
          <keystore>#{SIGNING_KEY}</keystore>
          <type>elliptic-curve</type>
          <curve-name>P-256</curve-name>
        </signing-key>
      </signing-keys>
      <signature-verification-keys>
      </signature-verification-keys>
    </crypto>
    <caching-services>
      <default-caching-service>
        <data-source>default-datasource</data-source>
      </default-caching-service>
    </caching-services>
  </facilities>
  <processing xmlns="https://curity.se/ns/conf/base">
    <license-key>#{LICENSE_KEY}</license-key>
    <account-managers>
      <account-manager>
        <id>default-account-manager</id>
        <enable-registration>
          <account-verification-method>no-verification</account-verification-method>
        </enable-registration>
        <account-data-source>default-datasource</account-data-source>
      </account-manager>
    </account-managers>
    <credential-managers>
      <credential-manager>
        <id>default-credential-manager</id>
        <Sha2WithSha256>
        </Sha2WithSha256>
        <data-source-backed>
          <data-source-id>default-datasource</data-source-id>
        </data-source-backed>
      </credential-manager>
    </credential-managers>
  </processing>
  <nacm xmlns="urn:ietf:params:xml:ns:yang:ietf-netconf-acm">
    <write-default>permit</write-default>
    <groups>
      <group>
        <name>admin</name>
        <user-name>admin</user-name>
      </group>
    </groups>
    <rule-list>
      <name>admin</name>
      <group>admin</group>
      <rule>
        <name>any-access</name>
        <action>permit</action>
      </rule>
    </rule-list>
    <rule-list>
      <name>any-group</name>
      <group>*</group>
      <rule>
        <name>tailf-aaa-authentication</name>
        <module-name>tailf-aaa</module-name>
        <path>/aaa/authentication/users/user[name='$USER']</path>
        <access-operations>read update</access-operations>
        <action>permit</action>
      </rule>
      <rule>
        <name>tailf-aaa-user</name>
        <module-name>tailf-aaa</module-name>
        <path>/user[name='$USER']</path>
        <access-operations>create read update delete</access-operations>
        <action>permit</action>
      </rule>
      <rule>
        <name>tailf-webui-user</name>
        <module-name>tailf-webui</module-name>
        <path>/webui/data-stores/user-profile[username='$USER']</path>
        <access-operations>create read update delete</access-operations>
        <action>permit</action>
      </rule>
    </rule-list>
  </nacm>
  <aaa xmlns="http://tail-f.com/ns/aaa/1.1">
    <authentication>
      <users>
        <user>
          <name>admin</name>
          <uid>0</uid>
          <gid>0</gid>
          <password>#{ADMIN_PASSWORD}</password>
          <ssh_keydir>/opt/idsvr/home/admin/.ssh</ssh_keydir>
          <homedir>/opt/idsvr/home/admin</homedir>
        </user>
      </users>
    </authentication>
    <ios>
      <level>
        <nr>0</nr>
        <prompt>\h> </prompt>
      </level>
      <level>
        <nr>15</nr>
        <prompt>\h# </prompt>
      </level>
      <privilege>
        <mode>exec</mode>
        <level>
          <nr>0</nr>
          <command>
            <name>action</name>
          </command>
          <command>
            <name>autowizard</name>
          </command>
          <command>
            <name>enable</name>
          </command>
          <command>
            <name>exit</name>
          </command>
          <command>
            <name>help</name>
          </command>
          <command>
            <name>startup</name>
          </command>
        </level>
        <level>
          <nr>15</nr>
          <command>
            <name>configure</name>
          </command>
        </level>
      </privilege>
    </ios>
  </aaa>
</config>